tempus/__init__.py
tempus/edge/__init__.py
tempus/edge/proto/JsonDataMessage_pb2.py
tempus/edge/proto/MessageProtocols_pb2.py
tempus/edge/proto/MessageTypes_pb2.py
tempus/edge/proto/MqttConfig_pb2.py
tempus/edge/proto/MqttMessage_pb2.py
tempus/edge/proto/OpcConfig_pb2.py
tempus/edge/proto/OpcMessage_pb2.py
tempus/edge/proto/TrackConfig_pb2.py
tempus/edge/proto/TrackMetadata_pb2.py
tempus/edge/proto/__init__.py
tempus.edge.proto-0.0.11.dev0.dist-info/DESCRIPTION.rst
tempus.edge.proto-0.0.11.dev0.dist-info/METADATA
tempus.edge.proto-0.0.11.dev0.dist-info/RECORD
tempus.edge.proto-0.0.11.dev0.dist-info/WHEEL
tempus.edge.proto-0.0.11.dev0.dist-info/metadata.json
tempus.edge.proto-0.0.11.dev0.dist-info/top_level.txt
