Metadata-Version: 2.0
Name: tempus.edge.proto
Version: 0.0.11.dev0
Summary: Tempus Edge protobuf definitions compiled into a python package.
Home-page: https://github.com/hashmapinc/tempus-edge
Author: Randy Pitcher
Author-email: randy.pitcher@hashmapinc.com
License: Apache License 2.0
Keywords: hashmap hashmapinc tempus edge iot protobuf
Platform: UNKNOWN
Requires-Dist: protobuf
